prometheus_build_info/__init__.py
prometheus_build_info/builder.py
prometheus_build_info/metrics.py
prometheus_build_info-2.0.2.dist-info/LICENSE
prometheus_build_info-2.0.2.dist-info/METADATA
prometheus_build_info-2.0.2.dist-info/WHEEL
prometheus_build_info-2.0.2.dist-info/entry_points.txt
prometheus_build_info-2.0.2.dist-info/top_level.txt
prometheus_build_info-2.0.2.dist-info/RECORD
