Metadata-Version: 2.1
Name: prometheus-build-info
Version: 2.0.2
Summary: Utility project for recording build information and exposing it as a prometheus metric
Home-page: https://github.com/nralbers/prometheus_buildinfo
Author: Niels Albers
Author-email: nralbers@gmail.com
License: MIT
Keywords: metrics,prometheus,build
Platform: UNKNOWN
Classifier: Natural Language :: English
Classifier: Programming Language :: Python :: 3
Classifier: Programming Language :: Python :: 3.5
Classifier: Programming Language :: Python :: 3.6
Classifier: Programming Language :: Python :: 3.7
Classifier: Programming Language :: Python :: 3.8
Classifier: Programming Language :: Python :: 3.9
Classifier: Programming Language :: Python :: 3.10
Classifier: Programming Language :: Python :: Implementation :: CPython
Classifier: Programming Language :: Python :: Implementation :: PyPy
Classifier: License :: OSI Approved :: MIT License
Classifier: Operating System :: OS Independent
Classifier: Development Status :: 5 - Production/Stable
Classifier: Topic :: Software Development :: Libraries :: Python Modules
Classifier: Topic :: System :: Monitoring
Classifier: Topic :: Software Development :: Build Tools
Classifier: Intended Audience :: Developers
Requires-Python: >=3.5
Requires-Dist: click
Requires-Dist: prometheus-client
